setup.cfg
setup.py
douban/__init__.py
douban/books_api.py
douban/cli.py
douban/movies_api.py
douban.cli.egg-info/PKG-INFO
douban.cli.egg-info/SOURCES.txt
douban.cli.egg-info/dependency_links.txt
douban.cli.egg-info/entry_points.txt
douban.cli.egg-info/requires.txt
douban.cli.egg-info/top_level.txt
douban.cli.egg-info/zip-safe