Metadata-Version: 1.0
Name: douban.cli
Version: 0.0.4
Summary: A dead simple douban cli based on Python
Home-page: UNKNOWN
Author: easonhan
Author-email: nbkhic@qq.com
License: MIT
Keywords: python douban douban.cli terminal
Platform: UNKNOWN
